Bullseye/__init__.py
Bullseye/bullseye_graph.py
Bullseye/graph.py
Bullseye/graph_aux.py
Bullseye/predefined_functions.py
Bullseye/sampling.py
Bullseye/utils.py
Bullseye/warning_handler.py
Bullseye/Tests/__init__.py
Bullseye/Tests/simple_test.py
bullseye_method-0.0.1.dist-info/LICENSE.txt
bullseye_method-0.0.1.dist-info/METADATA
bullseye_method-0.0.1.dist-info/WHEEL
bullseye_method-0.0.1.dist-info/top_level.txt
bullseye_method-0.0.1.dist-info/RECORD
